chesscalc/__init__.py
chesscalc/calculate.py
chesscalc/apsw/__init__.py
chesscalc/apsw/database.py
chesscalc/apsw/database_du.py
chesscalc/basecore/__init__.py
chesscalc/basecore/database.py
chesscalc/berkeleydb/__init__.py
chesscalc/berkeleydb/database.py
chesscalc/berkeleydb/database_du.py
chesscalc/core/__init__.py
chesscalc/core/apply_identities.py
chesscalc/core/calculate.py
chesscalc/core/configuration.py
chesscalc/core/constants.py
chesscalc/core/delete_games.py
chesscalc/core/eventrecord.py
chesscalc/core/export.py
chesscalc/core/filespec.py
chesscalc/core/gamerecord.py
chesscalc/core/identify_event.py
chesscalc/core/identify_item.py
chesscalc/core/identify_mode.py
chesscalc/core/identify_person.py
chesscalc/core/identify_playertype.py
chesscalc/core/identify_termination.py
chesscalc/core/identify_timecontrol.py
chesscalc/core/identity.py
chesscalc/core/mirror_identities.py
chesscalc/core/moderecord.py
chesscalc/core/name_lookup.py
chesscalc/core/person.py
chesscalc/core/pgnheaders.py
chesscalc/core/playerrecord.py
chesscalc/core/playertyperecord.py
chesscalc/core/population.py
chesscalc/core/selectorrecord.py
chesscalc/core/tab_from_selection.py
chesscalc/core/terminationrecord.py
chesscalc/core/timecontrolrecord.py
chesscalc/core/update_rule.py
chesscalc/core/utilities.py
chesscalc/db/__init__.py
chesscalc/db/database.py
chesscalc/db/database_du.py
chesscalc/db_tkinter/__init__.py
chesscalc/db_tkinter/database.py
chesscalc/db_tkinter/database_du.py
chesscalc/dpt/__init__.py
chesscalc/dpt/database.py
chesscalc/dpt/database_du.py
chesscalc/dpt/dptnofistat.py
chesscalc/gui/__init__.py
chesscalc/gui/calculator.py
chesscalc/gui/events.py
chesscalc/gui/eventsgrid.py
chesscalc/gui/eventspec.py
chesscalc/gui/eventsrow.py
chesscalc/gui/games.py
chesscalc/gui/gamesgrid.py
chesscalc/gui/gamesrow.py
chesscalc/gui/gridlocator.py
chesscalc/gui/help_.py
chesscalc/gui/modes.py
chesscalc/gui/modesgrid.py
chesscalc/gui/modesrow.py
chesscalc/gui/performancedu.py
chesscalc-2.0.4.dist-info/licenses/LICENCE
chesscalc-2.0.4.dist-info/METADATA
chesscalc-2.0.4.dist-info/WHEEL
chesscalc-2.0.4.dist-info/top_level.txt
chesscalc-2.0.4.dist-info/RECORD
