Metadata-Version: 2.4
Name: chesscalc
Version: 2.0.4
Summary: Calculate player performances in chess games.
Author-email: Roger Marsh <roger.marsh@solentware.co.uk>
License-Expression: BSD-3-Clause
Project-URL: Homepage, http://www.solentware.co.uk
Project-URL: Repository, https://github.com/RogerMarsh/chesscalc.git
Project-URL: Bug Tracker, https://github.com/RogerMarsh/chesscalc/issues
Classifier: Programming Language :: Python :: 3.9
Classifier: Programming Language :: Python :: 3.10
Classifier: Programming Language :: Python :: 3.11
Classifier: Programming Language :: Python :: 3.12
Classifier: Operating System :: OS Independent
Classifier: Topic :: Games/Entertainment :: Board Games
Classifier: Intended Audience :: End Users/Desktop
Classifier: Intended Audience :: Developers
Classifier: Development Status :: 3 - Alpha
License-File: LICENCE
Requires-Dist: solentware-misc==1.7.2
Requires-Dist: solentware-base==5.3
Requires-Dist: solentware-grid==3.0.2
Requires-Dist: pgn-read==2.6
Dynamic: license-file
